tfs/__init__.py
tfs/collection.py
tfs/constants.py
tfs/errors.py
tfs/frame.py
tfs/hdf.py
tfs/reader.py
tfs/testing.py
tfs/tools.py
tfs/writer.py
tfs_pandas-4.0.1.dist-info/METADATA
tfs_pandas-4.0.1.dist-info/WHEEL
tfs_pandas-4.0.1.dist-info/licenses/LICENSE
tfs_pandas-4.0.1.dist-info/RECORD
